{
  "version": 3,
  "middleware": {
    "/": {
      "files": [
        "server/edge-runtime-webpack.js",
        "server/middleware.js"
      ],
      "name": "middleware",
      "page": "/",
      "matchers": [
        {
          "regexp": "^(?:\\/(_next\\/data\\/[^/]{1,}))?(?:\\/((?!_next\\/static|_next\\/image|favicon.ico).*))(.json)?[\\/#\\?]?$",
          "originalSource": "/((?!_next/static|_next/image|favicon.ico).*)"
        }
      ],
      "wasm": [],
      "assets": [],
      "env": {
        "__NEXT_BUILD_ID": "5qDPEzEH3VDmMZ6dmzVCy",
        "NEXT_SERVER_ACTIONS_ENCRYPTION_KEY": "Mq4lUsnqYqroS061l6rYcVjdt10bu+bu7Xb8sqGXxYY=",
        "__NEXT_PREVIEW_MODE_ID": "3a45735e5ba985635ab27d9cd345bd36",
        "__NEXT_PREVIEW_MODE_ENCRYPTION_KEY": "07a19c8aa582bd4c89fcbb2a931938197fd666e48d7c656b78d9d29fb5b04570",
        "__NEXT_PREVIEW_MODE_SIGNING_KEY": "5199117da9e474ab87b3830b60d0ec05a163aeded5cf7edb433a4541e97008b0"
      }
    }
  },
  "functions": {},
  "sortedMiddleware": [
    "/"
  ]
}